LICENSE
README.md
setup.cfg
setup.py
prometheus_ecs_cluster_exporter.egg-info/PKG-INFO
prometheus_ecs_cluster_exporter.egg-info/SOURCES.txt
prometheus_ecs_cluster_exporter.egg-info/dependency_links.txt
prometheus_ecs_cluster_exporter.egg-info/entry_points.txt
prometheus_ecs_cluster_exporter.egg-info/not-zip-safe
prometheus_ecs_cluster_exporter.egg-info/requires.txt
prometheus_ecs_cluster_exporter.egg-info/top_level.txt
src/__init__.py
src/__main__.py
src/get_metrics.py
src/logger.py
src/prom_metrics.py